{"DocumentConnection":{"type":"DocumentConnection","resolveType":"multiCollectionDocumentList","collections":["sermons","events","blog","staff","gallery","pages","settings"]},"Node":{"type":"Node","resolveType":"nodeDocument"},"DocumentNode":{"type":"DocumentNode","resolveType":"multiCollectionDocument","createDocument":"create","updateDocument":"update"},"Sermons":{"type":"Sermons","resolveType":"collectionDocument","collection":"sermons","createSermons":"create","updateSermons":"update"},"SermonsConnection":{"type":"SermonsConnection","resolveType":"collectionDocumentList","collection":"sermons"},"Events":{"type":"Events","resolveType":"collectionDocument","collection":"events","createEvents":"create","updateEvents":"update"},"EventsConnection":{"type":"EventsConnection","resolveType":"collectionDocumentList","collection":"events"},"Blog":{"type":"Blog","resolveType":"collectionDocument","collection":"blog","createBlog":"create","updateBlog":"update"},"BlogConnection":{"type":"BlogConnection","resolveType":"collectionDocumentList","collection":"blog"},"Staff":{"type":"Staff","resolveType":"collectionDocument","collection":"staff","createStaff":"create","updateStaff":"update"},"StaffConnection":{"type":"StaffConnection","resolveType":"collectionDocumentList","collection":"staff"},"Gallery":{"type":"Gallery","resolveType":"collectionDocument","collection":"gallery","createGallery":"create","updateGallery":"update"},"GalleryConnection":{"type":"GalleryConnection","resolveType":"collectionDocumentList","collection":"gallery"},"Pages":{"type":"Pages","resolveType":"collectionDocument","collection":"pages","createPages":"create","updatePages":"update"},"PagesConnection":{"type":"PagesConnection","resolveType":"collectionDocumentList","collection":"pages"},"Settings":{"type":"Settings","resolveType":"collectionDocument","collection":"settings","createSettings":"create","updateSettings":"update"},"SettingsConnection":{"type":"SettingsConnection","resolveType":"collectionDocumentList","collection":"settings"}}